{
  "meta": {
    "id": "MX_1_A",
    "countryCode": "MX",
    "countryName": "Mexico",
    "difficulty": 1,
    "variant": "A",
    "region": "north-america",
    "continent": "Americas",
    "neighborCount": 3,
    "answerMode": "multiple_choice",
    "neighborLabels": 1,
    "choiceCount": 4,
    "distractorStrategy": "random",
    "renderStatus": "untested",
    "approved": true,
    "createdAt": "2026-06-04T17:12:09.801Z"
  },
  "puzzle": {
    "type": "hidden_country",
    "center": "MX",
    "visibleNeighbors": [
      "US",
      "GT",
      "BZ"
    ],
    "choices": [
      "GP",
      "NI",
      "MX",
      "KN"
    ],
    "correctAnswer": "MX",
    "svgMap": "/images/maps/region_world_northAmericaLow.svg",
    "region": "north-america"
  }
}