{
  "meta": {
    "id": "asia_LB_5_A",
    "countryCode": "LB",
    "countryName": "Lebanon",
    "difficulty": 5,
    "variant": "A",
    "region": "asia",
    "continent": "Asia",
    "neighborCount": 2,
    "answerMode": "free_text",
    "neighborLabels": 0,
    "choiceCount": 0,
    "distractorStrategy": "random",
    "renderStatus": "untested",
    "approved": true,
    "createdAt": "2026-06-04T20:57:30.117Z"
  },
  "puzzle": {
    "type": "missing_neighbor",
    "center": "LB",
    "visibleNeighbors": [
      "IL"
    ],
    "labeledNeighbors": [],
    "hiddenNeighbors": [
      "SY"
    ],
    "contextCountries": [],
    "choices": [],
    "correctAnswer": "SY",
    "svgMap": "/images/maps/region_world_asiaLow.svg",
    "region": "asia"
  }
}