{
  "meta": {
    "id": "MN_3_A",
    "countryCode": "MN",
    "countryName": "Mongolia",
    "difficulty": 3,
    "variant": "A",
    "region": "asia",
    "continent": "Asia",
    "neighborCount": 2,
    "answerMode": "multiple_choice",
    "neighborLabels": 0.2,
    "choiceCount": 4,
    "distractorStrategy": "random",
    "renderStatus": "untested",
    "approved": true,
    "createdAt": "2026-06-04T17:12:09.647Z"
  },
  "puzzle": {
    "type": "missing_neighbor",
    "center": "MN",
    "visibleNeighbors": [
      "CN"
    ],
    "labeledNeighbors": [],
    "hiddenNeighbors": [
      "RU"
    ],
    "contextCountries": [
      "VN",
      "OM"
    ],
    "choices": [
      "RU",
      "OM",
      "CN",
      "VN"
    ],
    "correctAnswer": "RU",
    "svgMap": "/images/maps/region_world_asiaLow.svg",
    "region": "asia"
  }
}