{
  "meta": {
    "id": "BG_5_A",
    "countryCode": "BG",
    "countryName": "Bulgaria",
    "difficulty": 5,
    "variant": "A",
    "region": "europe",
    "continent": "Europe",
    "neighborCount": 5,
    "answerMode": "free_text",
    "neighborLabels": 0,
    "choiceCount": 0,
    "distractorStrategy": "random",
    "renderStatus": "untested",
    "approved": true,
    "createdAt": "2026-06-04T17:11:54.840Z"
  },
  "puzzle": {
    "type": "missing_neighbor",
    "center": "BG",
    "visibleNeighbors": [
      "TR",
      "RO",
      "MK",
      "GR"
    ],
    "labeledNeighbors": [],
    "hiddenNeighbors": [
      "RS"
    ],
    "contextCountries": [],
    "choices": [],
    "correctAnswer": "RS",
    "svgMap": "/images/maps/region_world_europeLow.svg",
    "region": "europe"
  }
}